odoo8_addon_product_variant_sale_price-8.0.1.0.0.99.dev28-py3.8-nspkg.pth
odoo_addons/product_variant_sale_price/README.rst
odoo_addons/product_variant_sale_price/__init__.py
odoo_addons/product_variant_sale_price/__openerp__.py
odoo_addons/product_variant_sale_price/hooks.py
odoo_addons/product_variant_sale_price/i18n/ca.po
odoo_addons/product_variant_sale_price/i18n/de.po
odoo_addons/product_variant_sale_price/i18n/el_GR.po
odoo_addons/product_variant_sale_price/i18n/es.po
odoo_addons/product_variant_sale_price/i18n/es_ES.po
odoo_addons/product_variant_sale_price/i18n/es_MX.po
odoo_addons/product_variant_sale_price/i18n/eu.po
odoo_addons/product_variant_sale_price/i18n/fi.po
odoo_addons/product_variant_sale_price/i18n/fr.po
odoo_addons/product_variant_sale_price/i18n/fr_CH.po
odoo_addons/product_variant_sale_price/i18n/fr_FR.po
odoo_addons/product_variant_sale_price/i18n/gl.po
odoo_addons/product_variant_sale_price/i18n/hr.po
odoo_addons/product_variant_sale_price/i18n/hr_HR.po
odoo_addons/product_variant_sale_price/i18n/it.po
odoo_addons/product_variant_sale_price/i18n/nl.po
odoo_addons/product_variant_sale_price/i18n/nl_NL.po
odoo_addons/product_variant_sale_price/i18n/product_variant_sale_price.pot
odoo_addons/product_variant_sale_price/i18n/pt.po
odoo_addons/product_variant_sale_price/i18n/pt_BR.po
odoo_addons/product_variant_sale_price/i18n/ro.po
odoo_addons/product_variant_sale_price/i18n/ru.po
odoo_addons/product_variant_sale_price/i18n/sk.po
odoo_addons/product_variant_sale_price/i18n/sl.po
odoo_addons/product_variant_sale_price/i18n/tr.po
odoo_addons/product_variant_sale_price/i18n/tr_TR.po
odoo_addons/product_variant_sale_price/i18n/vi_VN.po
odoo_addons/product_variant_sale_price/i18n/zh_CN.po
odoo_addons/product_variant_sale_price/models/__init__.py
odoo_addons/product_variant_sale_price/models/product_product.py
odoo_addons/product_variant_sale_price/static/description/icon.png
odoo_addons/product_variant_sale_price/tests/__init__.py
odoo8_addon_product_variant_sale_price-8.0.1.0.0.99.dev28.dist-info/METADATA
odoo8_addon_product_variant_sale_price-8.0.1.0.0.99.dev28.dist-info/WHEEL
odoo8_addon_product_variant_sale_price-8.0.1.0.0.99.dev28.dist-info/namespace_packages.txt
odoo8_addon_product_variant_sale_price-8.0.1.0.0.99.dev28.dist-info/top_level.txt
odoo8_addon_product_variant_sale_price-8.0.1.0.0.99.dev28.dist-info/RECORD
